Metadata-Version: 1.0
Name: armoury
Version: 0.1.dev2
Summary: Collection of utility methods.
Home-page: https://github.com/nitingupta89/Armoury
Author: Nitin Gupta
Author-email: nitinguptawebdev@gmail.com
License: MIT
Platform: UNKNOWN
